ZYOpentracingGrpc/__init__.py
ZYOpentracingGrpc/_client.py
ZYOpentracingGrpc/_server.py
ZYOpentracingGrpc/_utilities.py
ZYOpentracingGrpc/grpcext/__init__.py
ZYOpentracingGrpc/grpcext/_interceptor.py
ZYOpentracingGrpcio-1.7.dist-info/LICENSE
ZYOpentracingGrpcio-1.7.dist-info/METADATA
ZYOpentracingGrpcio-1.7.dist-info/WHEEL
ZYOpentracingGrpcio-1.7.dist-info/top_level.txt
ZYOpentracingGrpcio-1.7.dist-info/RECORD
